enkacard2/enc_error.py
enkacard2/encbanner2.py
enkacard2/src/assets/Artist.png
enkacard2/src/assets/constant/ANEMO.png
enkacard2/src/assets/constant/CLOSED.png
enkacard2/src/assets/constant/CLOSED_BG.png
enkacard2/src/assets/constant/CONSTATN_BG.png
enkacard2/src/assets/constant/CRYO.png
enkacard2/src/assets/constant/DENDRO.png
enkacard2/src/assets/constant/ELECTRO.png
enkacard2/src/assets/constant/ERROR.png
enkacard2/src/assets/constant/GEO.png
enkacard2/src/assets/constant/GYDRO.png
enkacard2/src/assets/constant/PYRO.png
enkacard2/src/assets/font/Genshin_Impact.ttf
enkacard2/src/assets/font/GSEnochian.ttf
enkacard2/src/assets/icon/ANEMO.png
enkacard2/src/assets/icon/ANEMO_UP.png
enkacard2/src/assets/icon/ARTIFACT.png
enkacard2/src/assets/icon/ATTACK.png
enkacard2/src/assets/icon/ATTACK_PERCENT.png
enkacard2/src/assets/icon/CdReduction_primary.png
enkacard2/src/assets/icon/CHARGE_EFFICIENCY.png
enkacard2/src/assets/icon/CRITICAL.png
enkacard2/src/assets/icon/CRITICAL_HURT.png
enkacard2/src/assets/icon/CRYO.png
enkacard2/src/assets/icon/CRYO_UP.png
enkacard2/src/assets/icon/DEFENSE.png
enkacard2/src/assets/icon/DEFENSE_PERCENT.png
enkacard2/src/assets/icon/DENDRO.png
enkacard2/src/assets/icon/DENDRO_UP.png
enkacard2/src/assets/icon/ELECTRO.png
enkacard2/src/assets/icon/ELECTRO_UP.png
enkacard2/src/assets/icon/FIGHT_PROP_SHIELD_COST_MINUS_RATIO.png
enkacard2/src/assets/icon/FRIENDS.png
enkacard2/src/assets/icon/GEO.png
enkacard2/src/assets/icon/GEO_UP.png
enkacard2/src/assets/icon/HEAL.png
enkacard2/src/assets/icon/HEALED_ADD.png
enkacard2/src/assets/icon/HP.png
enkacard2/src/assets/icon/HP_PERCENT.png
enkacard2/src/assets/icon/HYDRO.png
enkacard2/src/assets/icon/HYDRO_UP.png
enkacard2/src/assets/icon/MASTERY.png
enkacard2/src/assets/icon/PHYSICAL_ADD_HURT.png
enkacard2/src/assets/icon/PYRO.png
enkacard2/src/assets/icon/PYRO_UP.png
enkacard2/src/assets/icon/SHIELD_COST_MINUS_RATIO.png
enkacard2/src/assets/InfoCharter/AvatarMaska.png
enkacard2-2.0.2.dist-info/METADATA
enkacard2-2.0.2.dist-info/WHEEL
enkacard2-2.0.2.dist-info/RECORD
