Metadata-Version: 2.1
Name: enkacard2
Version: 2.0.2
Summary: An asynchronous module and API that allows you to connect to your bot the generation of Genshin character cards from the Enka.Network website.
Home-page: https://github.com/DEViantUA/EnkaCard/tree/EnkaCard2
Author: None
Requires-Python: >=3.7,<4.0
Classifier: Programming Language :: Python :: 3
Classifier: Programming Language :: Python :: 3.7
Classifier: Programming Language :: Python :: 3.8
Classifier: Programming Language :: Python :: 3.9
Classifier: Programming Language :: Python :: 3.10
Classifier: Programming Language :: Python :: 3.11
Requires-Dist: Pillow (>=10.0.1,<11.0.0)
Requires-Dist: asyncache (>=0.3.1,<0.4.0)
Requires-Dist: cachetools (>=5.2.0,<6.0.0)
Requires-Dist: enkanetwork.py (>=1.4.5,<2.0.0)
Requires-Dist: numpy (>=1.24.2,<2.0.0)
Project-URL: Repository, https://github.com/DEViantUA/EnkaCard/tree/EnkaCard2
